batchling/__init__.py
batchling/__main__.py
batchling/cli/__init__.py
batchling/cli/callbacks.py
batchling/cli/completions.py
batchling/cli/enums.py
batchling/cli/main.py
batchling/db/__init__.py
batchling/db/crud.py
batchling/db/models.py
batchling/db/session.py
batchling/experiment.py
batchling/experiment_manager.py
batchling/models.py
batchling/providers/__init__.py
batchling/providers/anthropic.py
batchling/providers/gemini.py
batchling/providers/groq.py
batchling/providers/mistral.py
batchling/providers/openai.py
batchling/providers/together.py
batchling/request.py
batchling/utils/api.py
batchling/utils/classes.py
batchling/utils/files.py
batchling/utils/logging.py
batchling-0.0.14.dist-info/WHEEL
batchling-0.0.14.dist-info/entry_points.txt
batchling-0.0.14.dist-info/METADATA
batchling-0.0.14.dist-info/RECORD
