Metadata-Version: 2.3
Name: batchling
Version: 0.0.14
Summary: A python library to abstract GenAI Batch API usage
Author: Raphael Vienne
Author-email: Raphael Vienne <raphaelvienne.work@gmail.com>
Requires-Dist: click>=8.3.0
Requires-Dist: httpx>=0.28.1
Requires-Dist: platformdirs>=4.5.0
Requires-Dist: pydantic>=2.12.3
Requires-Dist: python-dotenv>=1.1.1
Requires-Dist: sqlalchemy>=2.0.44
Requires-Dist: structlog>=25.5.0
Requires-Dist: typer>=0.20.0
Requires-Python: >=3.12, <4.0
Project-URL: source, https://github.com/vienneraphael/batchling
